LICENSE
MANIFEST.in
README.md
setup.py
anago/__init__.py
anago/callbacks.py
anago/layers.py
anago/models.py
anago/preprocessing.py
anago/tagger.py
anago/trainer.py
anago/utils.py
anago/wrapper.py
anago_py3.7.egg-info/PKG-INFO
anago_py3.7.egg-info/SOURCES.txt
anago_py3.7.egg-info/dependency_links.txt
anago_py3.7.egg-info/requires.txt
anago_py3.7.egg-info/top_level.txt