Metadata-Version: 1.1
Name: anago-py3.7
Version: 1.0.10
Summary: Sequence labeling library using Keras. It is noted that this version has light modification by sonvx to run on Python3.7
Home-page: https://github.com/sonvx/anago
Author: Hironsan
Author-email: hiroki.nakayama.py@gmail.com
License: MIT
Platform: UNKNOWN
Classifier: License :: OSI Approved :: MIT License
Classifier: Programming Language :: Python
Classifier: Programming Language :: Python :: 3.6
Classifier: Programming Language :: Python :: 3.7
Classifier: Programming Language :: Python :: Implementation :: CPython
Classifier: Programming Language :: Python :: Implementation :: PyPy
